cpotp/__init__.py
cpotp/_version.py
cpotp/command_line.py
cpotp-0.0.8.dist-info/LICENSE
cpotp-0.0.8.dist-info/METADATA
cpotp-0.0.8.dist-info/WHEEL
cpotp-0.0.8.dist-info/entry_points.txt
cpotp-0.0.8.dist-info/top_level.txt
cpotp-0.0.8.dist-info/RECORD
