Metadata-Version: 2.1
Name: cpotp
Version: 0.0.8
Summary: Command line tool to copy the latest OTP received in the connected Android device to the clipboard.
Home-page: https://github.com/riteshpanjwani/cpotp
Author: Ritesh Panjwani
Author-email: riteshpanjwani@gmail.com
License: Apache-2.0 License
Keywords: cpotp,python,otp,copy otp,clipboard
Platform: UNKNOWN
Requires-Python: >=3.6
Requires-Dist: nltk
Requires-Dist: pyderman
Requires-Dist: pyperclip
Requires-Dist: selenium
